Workbook
Name NativeTimeline_Invoice_Date: #N/A
Name Slicer_Beverage_Brand: #N/A
Name Slicer_Region: #N/A
Name Slicer_Retailer: #N/A

Sheet Data
B2: Key American Coca-Cola Retailers
B3: Beverage Sales & Operating Margin 2021
A5: Column1 | B5: Retailer | C5: Retailer ID | D5: Invoice Date | E5: Region | F5: State | G5: City | H5: Beverage Brand | I5: Price per Unit | J5: Units Sold | K5: Total Sales | L5: Operating Profit | M5: Operating Margin
B6: Sodapop | C6: 1185732 | D6: 44210 | E6: Northeast | F6: New York | G6: New York | H6: Coca-Cola | I6: 0.5 | J6: 12000 | K6: =I6*J6 -> 6000 | L6: =K6*M6 -> 3000 | M6: 0.5
B7: Sodapop | C7: 1185732 | D7: 44210 | E7: Northeast | F7: New York | G7: New York | H7: Diet Coke | I7: 0.5 | J7: 10000 | K7: =I7*J7 -> 5000 | L7: =K7*M7 -> 1500 | M7: 0.3
B8: Sodapop | C8: 1185732 | D8: 44210 | E8: Northeast | F8: New York | G8: New York | H8: Sprite | I8: 0.4 | J8: 10000 | K8: =I8*J8 -> 4000 | L8: =K8*M8 -> 1400 | M8: 0.35
B9: Sodapop | C9: 1185732 | D9: 44210 | E9: Northeast | F9: New York | G9: New York | H9: Fanta | I9: 0.45 | J9: 8500 | K9: =I9*J9 -> 3825 | L9: =K9*M9 -> 1338.75 | M9: 0.35
B10: Sodapop | C10: 1185732 | D10: 44210 | E10: Northeast | F10: New York | G10: New York | H10: Powerade | I10: 0.6 | J10: 9000 | K10: =I10*J10 -> 5400 | L10: =K10*M10 -> 1620 | M10: 0.3
B11: Sodapop | C11: 1185732 | D11: 44210 | E11: Northeast | F11: New York | G11: New York | H11: Dasani Water | I11: 0.5 | J11: 10000 | K11: =I11*J11 -> 5000 | L11: =K11*M11 -> 1250 | M11: 0.25
B12: Sodapop | C12: 1185732 | D12: 44239 | E12: Northeast | F12: New York | G12: New York | H12: Coca-Cola | I12: 0.5 | J12: 12500 | K12: =I12*J12 -> 6250 | L12: =K12*M12 -> 3125 | M12: 0.5
B13: Sodapop | C13: 1185732 | D13: 44239 | E13: Northeast | F13: New York | G13: New York | H13: Diet Coke | I13: 0.5 | J13: 9000 | K13: =I13*J13 -> 4500 | L13: =K13*M13 -> 1350 | M13: 0.3
B14: Sodapop | C14: 1185732 | D14: 44239 | E14: Northeast | F14: New York | G14: New York | H14: Sprite | I14: 0.4 | J14: 9500 | K14: =I14*J14 -> 3800 | L14: =K14*M14 -> 1330 | M14: 0.35
B15: Sodapop | C15: 1185732 | D15: 44239 | E15: Northeast | F15: New York | G15: New York | H15: Fanta | I15: 0.45 | J15: 8250 | K15: =I15*J15 -> 3712.5 | L15: =K15*M15 -> 1299.375 | M15: 0.35
B16: Sodapop | C16: 1185732 | D16: 44239 | E16: Northeast | F16: New York | G16: New York | H16: Powerade | I16: 0.6 | J16: 9000 | K16: =I16*J16 -> 5400 | L16: =K16*M16 -> 1620 | M16: 0.3
B17: Sodapop | C17: 1185732 | D17: 44239 | E17: Northeast | F17: New York | G17: New York | H17: Dasani Water | I17: 0.5 | J17: 10000 | K17: =I17*J17 -> 5000 | L17: =K17*M17 -> 1250 | M17: 0.25
... B509: Sodapop | C509: 1185732 | D509: 44533 | E509: Northeast | F509: Pennsylvania | G509: Philadelphia | H509: Dasani Water | I509: 0.75 | J509: 2750 | K509: =I509*J509 -> 2062.5 | L509: =K509*M509 -> 618.75 | M509: 0.3
A510: x | B510: FizzySip | C510: 1128299 | D510: 44211 | E510: West | F510: Nevada | G510: Las Vegas | H510: Coca-Cola | I510: 0.35 | J510: 4500 | K510: =I510*J510 -> 1575 | L510: =K510*M510 -> 630 | M510: 0.4
B511: FizzySip | C511: 1128299 | D511: 44211 | E511: West | F511: Nevada | G511: Las Vegas | H511: Diet Coke | I511: 0.45 | J511: 4500 | K511: =I511*J511 -> 2025 | L511: =K511*M511 -> 506.25 | M511: 0.25
B512: FizzySip | C512: 1128299 | D512: 44211 | E512: West | F512: Nevada | G512: Las Vegas | H512: Sprite | I512: 0.45 | J512: 4500 | K512: =I512*J512 -> 2025 | L512: =K512*M512 -> 810 | M512: 0.4
B513: FizzySip | C513: 1128299 | D513: 44211 | E513: West | F513: Nevada | G513: Las Vegas | H513: Fanta | I513: 0.45 | J513: 3000 | K513: =I513*J513 -> 1350 | L513: =K513*M513 -> 472.5 | M513: 0.35
B514: FizzySip | C514: 1128299 | D514: 44211 | E514: West | F514: Nevada | G514: Las Vegas | H514: Powerade | I514: 0.5 | J514: 2500 | K514: =I514*J514 -> 1250 | L514: =K514*M514 -> 687.5 | M514: 0.55
B515: FizzySip | C515: 1128299 | D515: 44211 | E515: West | F515: Nevada | G515: Las Vegas | H515: Dasani Water | I515: 0.45 | J515: 4750 | K515: =I515*J515 -> 2137.5 | L515: =K515*M515 -> 427.5 | M515: 0.2
B516: FizzySip | C516: 1128299 | D516: 44242 | E516: West | F516: Nevada | G516: Las Vegas | H516: Coca-Cola | I516: 0.35 | J516: 5250 | K516: =I516*J516 -> 1837.5 | L516: =K516*M516 -> 735 | M516: 0.4
B517: FizzySip | C517: 1128299 | D517: 44242 | E517: West | F517: Nevada | G517: Las Vegas | H517: Diet Coke | I517: 0.45 | J517: 4250 | K517: =I517*J517 -> 1912.5 | L517: =K517*M517 -> 478.125 | M517: 0.25
B518: FizzySip | C518: 1128299 | D518: 44242 | E518: West | F518: Nevada | G518: Las Vegas | H518: Sprite | I518: 0.45 | J518: 4250 | K518: =I518*J518 -> 1912.5 | L518: =K518*M518 -> 765 | M518: 0.4
B519: FizzySip | C519: 1128299 | D519: 44242 | E519: West | F519: Nevada | G519: Las Vegas | H519: Fanta | I519: 0.45 | J519: 2750 | K519: =I519*J519 -> 1237.5 | L519: =K519*M519 -> 433.125 | M519: 0.35
B520: FizzySip | C520: 1128299 | D520: 44242 | E520: West | F520: Nevada | G520: Las Vegas | H520: Powerade | I520: 0.5 | J520: 2000 | K520: =I520*J520 -> 1000 | L520: =K520*M520 -> 550 | M520: 0.55
B521: FizzySip | C521: 1128299 | D521: 44242 | E521: West | F521: Nevada | G521: Las Vegas | H521: Dasani Water | I521: 0.45 | J521: 4000 | K521: =I521*J521 -> 1800 | L521: =K521*M521 -> 360 | M521: 0.2
B522: FizzySip | C522: 1128299 | D522: 44269 | E522: West | F522: Nevada | G522: Las Vegas | H522: Coca-Cola | I522: 0.45 | J522: 5500 | K522: =I522*J522 -> 2475 | L522: =K522*M522 -> 990 | M522: 0.4
... B581: FizzySip | C581: 1128299 | D581: 44544 | E581: West | F581: Nevada | G581: Las Vegas | H581: Dasani Water | I581: 0.75 | J581: 5000 | K581: =I581*J581 -> 3750 | L581: =K581*M581 -> 562.5 | M581: 0.15
A582: x | B582: FizzySip | C582: 1128299 | D582: 44201 | E582: West | F582: Colorado | G582: Denver | H582: Coca-Cola | I582: 0.3 | J582: 4250 | K582: =I582*J582 -> 1275 | L582: =K582*M582 -> 446.25 | M582: 0.35
B583: FizzySip | C583: 1128299 | D583: 44201 | E583: West | F583: Colorado | G583: Denver | H583: Diet Coke | I583: 0.4 | J583: 4250 | K583: =I583*J583 -> 1700 | L583: =K583*M583 -> 340 | M583: 0.2
B584: FizzySip | C584: 1128299 | D584: 44201 | E584: West | F584: Colorado | G584: Denver | H584: Sprite | I584: 0.4 | J584: 4250 | K584: =I584*J584 -> 1700 | L584: =K584*M584 -> 595 | M584: 0.35
B585: FizzySip | C585: 1128299 | D585: 44201 | E585: West | F585: Colorado | G585: Denver | H585: Fanta | I585: 0.4 | J585: 2750 | K585: =I585*J585 -> 1100 | L585: =K585*M585 -> 330 | M585: 0.3
B586: FizzySip | C586: 1128299 | D586: 44201 | E586: West | F586: Colorado | G586: Denver | H586: Powerade | I586: 0.45 | J586: 2250 | K586: =I586*J586 -> 1012.5 | L586: =K586*M586 -> 506.25 | M586: 0.5
B587: FizzySip | C587: 1128299 | D587: 44201 | E587: West | F587: Colorado | G587: Denver | H587: Dasani Water | I587: 0.4 | J587: 4750 | K587: =I587*J587 -> 1900 | L587: =K587*M587 -> 285 | M587: 0.15
B588: FizzySip | C588: 1128299 | D588: 44232 | E588: West | F588: Colorado | G588: Denver | H588: Coca-Cola | I588: 0.3 | J588: 5250 | K588: =I588*J588 -> 1575 | L588: =K588*M588 -> 551.25 | M588: 0.35
B589: FizzySip | C589: 1128299 | D589: 44232 | E589: West | F589: Colorado | G589: Denver | H589: Diet Coke | I589: 0.4 | J589: 4250 | K589: =I589*J589 -> 1700 | L589: =K589*M589 -> 340 | M589: 0.2
B590: FizzySip | C590: 1128299 | D590: 44232 | E590: West | F590: Colorado | G590: Denver | H590: Sprite | I590: 0.4 | J590: 4250 | K590: =I590*J590 -> 1700 | L590: =K590*M590 -> 595 | M590: 0.35
B591: FizzySip | C591: 1128299 | D591: 44232 | E591: West | F591: Colorado | G591: Denver | H591: Fanta | I591: 0.4 | J591: 2750 | K591: =I591*J591 -> 1100 | L591: =K591*M591 -> 330 | M591: 0.3
B592: FizzySip | C592: 1128299 | D592: 44232 | E592: West | F592: Colorado | G592: Denver | H592: Powerade | I592: 0.45 | J592: 2000 | K592: =I592*J592 -> 900 | L592: =K592*M592 -> 450 | M592: 0.5
B593: FizzySip | C593: 1128299 | D593: 44232 | E593: West | F593: Colorado | G593: Denver | H593: Dasani Water | I593: 0.4 | J593: 4000 | K593: =I593*J593 -> 1600 | L593: =K593*M593 -> 240 | M593: 0.15
B594: FizzySip | C594: 1128299 | D594: 44259 | E594: West | F594: Colorado | G594: Denver | H594: Coca-Cola | I594: 0.4 | J594: 5500 | K594: =I594*J594 -> 2200 | L594: =K594*M594 -> 770 | M594: 0.35
... B653: FizzySip | C653: 1128299 | D653: 44534 | E653: West | F653: Colorado | G653: Denver | H653: Dasani Water | I653: 0.8 | J653: 5250 | K653: =I653*J653 -> 4200 | L653: =K653*M653 -> 840 | M653: 0.2
A654: x | B654: FizzySip | C654: 1128299 | D654: 44199 | E654: West | F654: Washington | G654: Seattle | H654: Coca-Cola | I654: 0.4 | J654: 4500 | K654: =I654*J654 -> 1800 | L654: =K654*M654 -> 540 | M654: 0.3
B655: FizzySip | C655: 1128299 | D655: 44199 | E655: West | F655: Washington | G655: Seattle | H655: Diet Coke | I655: 0.5 | J655: 4500 | K655: =I655*J655 -> 2250 | L655: =K655*M655 -> 562.5 | M655: 0.25
B656: FizzySip | C656: 1128299 | D656: 44199 | E656: West | F656: Washington | G656: Seattle | H656: Sprite | I656: 0.5 | J656: 4500 | K656: =I656*J656 -> 2250 | L656: =K656*M656 -> 562.5 | M656: 0.25
B657: FizzySip | C657: 1128299 | D657: 44199 | E657: West | F657: Washington | G657: Seattle | H657: Fanta | I657: 0.5 | J657: 3000 | K657: =I657*J657 -> 1500 | L657: =K657*M657 -> 450 | M657: 0.3
B658: FizzySip | C658: 1128299 | D658: 44199 | E658: West | F658: Washington | G658: Seattle | H658: Powerade | I658: 0.55 | J658: 2500 | K658: =I658*J658 -> 1375 | L658: =K658*M658 -> 343.75 | M658: 0.25
B659: FizzySip | C659: 1128299 | D659: 44199 | E659: West | F659: Washington | G659: Seattle | H659: Dasani Water | I659: 0.5 | J659: 5000 | K659: =I659*J659 -> 2500 | L659: =K659*M659 -> 500 | M659: 0.2
B660: FizzySip | C660: 1128299 | D660: 44230 | E660: West | F660: Washington | G660: Seattle | H660: Coca-Cola | I660: 0.4 | J660: 5500 | K660: =I660*J660 -> 2200 | L660: =K660*M660 -> 660 | M660: 0.3
B661: FizzySip | C661: 1128299 | D661: 44230 | E661: West | F661: Washington | G661: Seattle | H661: Diet Coke | I661: 0.5 | J661: 4500 | K661: =I661*J661 -> 2250 | L661: =K661*M661 -> 562.5 | M661: 0.25
B662: FizzySip | C662: 1128299 | D662: 44230 | E662: West | F662: Washington | G662: Seattle | H662: Sprite | I662: 0.5 | J662: 4500 | K662: =I662*J662 -> 2250 | L662: =K662*M662 -> 562.5 | M662: 0.25
B663: FizzySip | C663: 1128299 | D663: 44230 | E663: West | F663: Washington | G663: Seattle | H663: Fanta | I663: 0.5 | J663: 3000 | K663: =I663*J663 -> 1500 | L663: =K663*M663 -> 450 | M663: 0.3
B664: FizzySip | C664: 1128299 | D664: 44230 | E664: West | F664: Washington | G664: Seattle | H664: Powerade | I664: 0.55 | J664: 2250 | K664: =I664*J664 -> 1237.5 | L664: =K664*M664 -> 309.375 | M664: 0.25
B665: FizzySip | C665: 1128299 | D665: 44230 | E665: West | F665: Washington | G665: Seattle | H665: Dasani Water | I665: 0.5 | J665: 4250 | K665: =I665*J665 -> 2125 | L665: =K665*M665 -> 425 | M665: 0.2
B666: FizzySip | C666: 1128299 | D666: 44257 | E666: West | F666: Washington | G666: Seattle | H666: Coca-Cola | I666: 0.5 | J666: 5750 | K666: =I666*J666 -> 2875 | L666: =K666*M666 -> 862.5 | M666: 0.3
... B725: FizzySip | C725: 1128299 | D725: 44532 | E725: West | F725: Washington | G725: Seattle | H725: Dasani Water | I725: 0.95 | J725: 5750 | K725: =I725*J725 -> 5462.5 | L725: =K725*M725 -> 1092.5 | M725: 0.2
A726: x | B726: Sodapop | C726: 1185732 | D726: 44208 | E726: Southeast | F726: Florida | G726: Miami | H726: Coca-Cola | I726: 0.45 | J726: 10500 | K726: =I726*J726 -> 4725 | L726: =K726*M726 -> 2126.25 | M726: 0.45 | P726: =Data!$I726+0.05 -> 0.5
B727: Sodapop | C727: 1185732 | D727: 44208 | E727: Southeast | F727: Florida | G727: Miami | H727: Diet Coke | I727: 0.45 | J727: 8500 | K727: =I727*J727 -> 3825 | L727: =K727*M727 -> 1338.75 | M727: 0.35 | P727: =Data!$I727+0.05 -> 0.5
B728: Sodapop | C728: 1185732 | D728: 44208 | E728: Southeast | F728: Florida | G728: Miami | H728: Sprite | I728: 0.35 | J728: 8500 | K728: =I728*J728 -> 2975 | L728: =K728*M728 -> 743.75 | M728: 0.25 | P728: =Data!$I728+0.05 -> 0.4
B729: Sodapop | C729: 1185732 | D729: 44208 | E729: Southeast | F729: Florida | G729: Miami | H729: Fanta | I729: 0.4 | J729: 7000 | K729: =I729*J729 -> 2800 | L729: =K729*M729 -> 840 | M729: 0.3 | P729: =Data!$I729+0.05 -> 0.45
B730: Sodapop | C730: 1185732 | D730: 44208 | E730: Southeast | F730: Florida | G730: Miami | H730: Powerade | I730: 0.55 | J730: 7500 | K730: =I730*J730 -> 4125 | L730: =K730*M730 -> 1443.75 | M730: 0.35 | P730: =Data!$I730+0.05 -> 0.6
B731: Sodapop | C731: 1185732 | D731: 44208 | E731: Southeast | F731: Florida | G731: Miami | H731: Dasani Water | I731: 0.45 | J731: 8500 | K731: =I731*J731 -> 3825 | L731: =K731*M731 -> 1912.5 | M731: 0.5 | P731: =Data!$I731+0.05 -> 0.5
B732: Sodapop | C732: 1185732 | D732: 44237 | E732: Southeast | F732: Florida | G732: Miami | H732: Coca-Cola | I732: 0.45 | J732: 11000 | K732: =I732*J732 -> 4950 | L732: =K732*M732 -> 2227.5 | M732: 0.45 | P732: =Data!$I732+0.05 -> 0.5
B733: Sodapop | C733: 1185732 | D733: 44237 | E733: Southeast | F733: Florida | G733: Miami | H733: Diet Coke | I733: 0.45 | J733: 7500 | K733: =I733*J733 -> 3375 | L733: =K733*M733 -> 1181.25 | M733: 0.35 | P733: =Data!$I733+0.05 -> 0.5
B734: Sodapop | C734: 1185732 | D734: 44237 | E734: Southeast | F734: Florida | G734: Miami | H734: Sprite | I734: 0.35 | J734: 8000 | K734: =I734*J734 -> 2800 | L734: =K734*M734 -> 700 | M734: 0.25 | P734: =Data!$I734+0.05 -> 0.4
B735: Sodapop | C735: 1185732 | D735: 44237 | E735: Southeast | F735: Florida | G735: Miami | H735: Fanta | I735: 0.4 | J735: 6750 | K735: =I735*J735 -> 2700 | L735: =K735*M735 -> 810 | M735: 0.3 | P735: =Data!$I735+0.05 -> 0.45
B736: Sodapop | C736: 1185732 | D736: 44237 | E736: Southeast | F736: Florida | G736: Miami | H736: Powerade | I736: 0.55 | J736: 7500 | K736: =I736*J736 -> 4125 | L736: =K736*M736 -> 1443.75 | M736: 0.35 | P736: =Data!$I736+0.05 -> 0.6
B737: Sodapop | C737: 1185732 | D737: 44237 | E737: Southeast | F737: Florida | G737: Miami | H737: Dasani Water | I737: 0.45 | J737: 8500 | K737: =I737*J737 -> 3825 | L737: =K737*M737 -> 1912.5 | M737: 0.5 | P737: =Data!$I737+0.05 -> 0.5
B738: Sodapop | C738: 1185732 | D738: 44263 | E738: Southeast | F738: Florida | G738: Miami | H738: Coca-Cola | I738: 0.45 | J738: 10700 | K738: =I738*J738 -> 4815 | L738: =K738*M738 -> 2166.75 | M738: 0.45 | P738: =Data!$I738+0.05 -> 0.5
... B797: Sodapop | C797: 1185732 | D797: 44538 | E797: Southeast | F797: Florida | G797: Miami | H797: Dasani Water | I797: 0.7 | J797: 8750 | K797: =I797*J797 -> 6125 | L797: =K797*M797 -> 3062.5 | M797: 0.5 | P797: =Data!$I797+0.05 -> 0.75
A798: x | B798: Sodapop | C798: 1185732 | D798: 44209 | E798: Midwest | F798: Minnesota | G798: Minneapolis | H798: Coca-Cola | I798: 0.35 | J798: 4500 | K798: =I798*J798 -> 1575 | L798: =K798*M798 -> 551.25 | M798: 0.35
B799: Sodapop | C799: 1185732 | D799: 44209 | E799: Midwest | F799: Minnesota | G799: Minneapolis | H799: Diet Coke | I799: 0.35 | J799: 2500 | K799: =I799*J799 -> 875 | L799: =K799*M799 -> 262.5 | M799: 0.3
B800: Sodapop | C800: 1185732 | D800: 44209 | E800: Midwest | F800: Minnesota | G800: Minneapolis | H800: Sprite | I800: 0.25 | J800: 2500 | K800: =I800*J800 -> 625 | L800: =K800*M800 -> 187.5 | M800: 0.3
B801: Sodapop | C801: 1185732 | D801: 44209 | E801: Midwest | F801: Minnesota | G801: Minneapolis | H801: Fanta | I801: 0.3 | J801: 1000 | K801: =I801*J801 -> 300 | L801: =K801*M801 -> 105 | M801: 0.35
B802: Sodapop | C802: 1185732 | D802: 44209 | E802: Midwest | F802: Minnesota | G802: Minneapolis | H802: Powerade | I802: 0.45 | J802: 1500 | K802: =I802*J802 -> 675 | L802: =K802*M802 -> 202.5 | M802: 0.3
B803: Sodapop | C803: 1185732 | D803: 44209 | E803: Midwest | F803: Minnesota | G803: Minneapolis | H803: Dasani Water | I803: 0.35 | J803: 2500 | K803: =I803*J803 -> 875 | L803: =K803*M803 -> 393.75 | M803: 0.45
B804: Sodapop | C804: 1185732 | D804: 44240 | E804: Midwest | F804: Minnesota | G804: Minneapolis | H804: Coca-Cola | I804: 0.35 | J804: 5000 | K804: =I804*J804 -> 1750 | L804: =K804*M804 -> 612.5 | M804: 0.35
B805: Sodapop | C805: 1185732 | D805: 44240 | E805: Midwest | F805: Minnesota | G805: Minneapolis | H805: Diet Coke | I805: 0.35 | J805: 1500 | K805: =I805*J805 -> 525 | L805: =K805*M805 -> 157.5 | M805: 0.3
B806: Sodapop | C806: 1185732 | D806: 44240 | E806: Midwest | F806: Minnesota | G806: Minneapolis | H806: Sprite | I806: 0.25 | J806: 2000 | K806: =I806*J806 -> 500 | L806: =K806*M806 -> 150 | M806: 0.3
B807: Sodapop | C807: 1185732 | D807: 44240 | E807: Midwest | F807: Minnesota | G807: Minneapolis | H807: Fanta | I807: 0.3 | J807: 750 | K807: =I807*J807 -> 225 | L807: =K807*M807 -> 78.75 | M807: 0.35
B808: Sodapop | C808: 1185732 | D808: 44240 | E808: Midwest | F808: Minnesota | G808: Minneapolis | H808: Powerade | I808: 0.45 | J808: 1500 | K808: =I808*J808 -> 675 | L808: =K808*M808 -> 202.5 | M808: 0.3
B809: Sodapop | C809: 1185732 | D809: 44240 | E809: Midwest | F809: Minnesota | G809: Minneapolis | H809: Dasani Water | I809: 0.35 | J809: 2250 | K809: =I809*J809 -> 787.5 | L809: =K809*M809 -> 354.375 | M809: 0.45
B810: Sodapop | C810: 1185732 | D810: 44267 | E810: Midwest | F810: Minnesota | G810: Minneapolis | H810: Coca-Cola | I810: 0.4 | J810: 4450 | K810: =I810*J810 -> 1780 | L810: =K810*M810 -> 623 | M810: 0.35
... B869: Sodapop | C869: 1185732 | D869: 44542 | E869: Midwest | F869: Minnesota | G869: Minneapolis | H869: Dasani Water | I869: 0.6 | J869: 2750 | K869: =I869*J869 -> 1650 | L869: =K869*M869 -> 742.5 | M869: 0.45
A870: x | B870: DreamCo | C870: 1189833 | D870: 44213 | E870: Midwest | F870: Montana | G870: Billings | H870: Coca-Cola | I870: 0.35 | J870: 4750 | K870: =I870*J870 -> 1662.5 | L870: =K870*M870 -> 748.125 | M870: 0.45
B871: DreamCo | C871: 1189833 | D871: 44213 | E871: Midwest | F871: Montana | G871: Billings | H871: Diet Coke | I871: 0.45 | J871: 4750 | K871: =I871*J871 -> 2137.5 | L871: =K871*M871 -> 641.25 | M871: 0.3
B872: DreamCo | C872: 1189833 | D872: 44213 | E872: Midwest | F872: Montana | G872: Billings | H872: Sprite | I872: 0.45 | J872: 4750 | K872: =I872*J872 -> 2137.5 | L872: =K872*M872 -> 961.875 | M872: 0.45
B873: DreamCo | C873: 1189833 | D873: 44213 | E873: Midwest | F873: Montana | G873: Billings | H873: Fanta | I873: 0.45 | J873: 3250 | K873: =I873*J873 -> 1462.5 | L873: =K873*M873 -> 585 | M873: 0.4
B874: DreamCo | C874: 1189833 | D874: 44213 | E874: Midwest | F874: Montana | G874: Billings | H874: Powerade | I874: 0.5 | J874: 2750 | K874: =I874*J874 -> 1375 | L874: =K874*M874 -> 825 | M874: 0.6
B875: DreamCo | C875: 1189833 | D875: 44213 | E875: Midwest | F875: Montana | G875: Billings | H875: Dasani Water | I875: 0.45 | J875: 4750 | K875: =I875*J875 -> 2137.5 | L875: =K875*M875 -> 534.375 | M875: 0.25
B876: DreamCo | C876: 1189833 | D876: 44244 | E876: Midwest | F876: Montana | G876: Billings | H876: Coca-Cola | I876: 0.35 | J876: 5250 | K876: =I876*J876 -> 1837.5 | L876: =K876*M876 -> 826.875 | M876: 0.45
B877: DreamCo | C877: 1189833 | D877: 44244 | E877: Midwest | F877: Montana | G877: Billings | H877: Diet Coke | I877: 0.45 | J877: 4250 | K877: =I877*J877 -> 1912.5 | L877: =K877*M877 -> 573.75 | M877: 0.3
B878: DreamCo | C878: 1189833 | D878: 44244 | E878: Midwest | F878: Montana | G878: Billings | H878: Sprite | I878: 0.45 | J878: 4500 | K878: =I878*J878 -> 2025 | L878: =K878*M878 -> 911.25 | M878: 0.45
B879: DreamCo | C879: 1189833 | D879: 44244 | E879: Midwest | F879: Montana | G879: Billings | H879: Fanta | I879: 0.45 | J879: 3000 | K879: =I879*J879 -> 1350 | L879: =K879*M879 -> 540 | M879: 0.4
B880: DreamCo | C880: 1189833 | D880: 44244 | E880: Midwest | F880: Montana | G880: Billings | H880: Powerade | I880: 0.5 | J880: 2250 | K880: =I880*J880 -> 1125 | L880: =K880*M880 -> 675 | M880: 0.6
B881: DreamCo | C881: 1189833 | D881: 44244 | E881: Midwest | F881: Montana | G881: Billings | H881: Dasani Water | I881: 0.45 | J881: 4250 | K881: =I881*J881 -> 1912.5 | L881: =K881*M881 -> 478.125 | M881: 0.25
B882: DreamCo | C882: 1189833 | D882: 44271 | E882: Midwest | F882: Montana | G882: Billings | H882: Coca-Cola | I882: 0.35 | J882: 5750 | K882: =I882*J882 -> 2012.5 | L882: =K882*M882 -> 905.625 | M882: 0.45
... B941: DreamCo | C941: 1189833 | D941: 44546 | E941: Midwest | F941: Montana | G941: Billings | H941: Dasani Water | I941: 0.6 | J941: 5000 | K941: =I941*J941 -> 3000 | L941: =K941*M941 -> 750 | M941: 0.25
...

Sheet Piviot Tables
A3: Sum of Total Sales | B3: Sum of Units Sold | C3: Sum of Operating Profit | D3: Average of Operating Margin
A4: 8684027.5 | B4: 17148250 | C4: 3173631.9 | D4: 0.36310442
A9: Row Labels | B9: Sum of Total Sales
A10: Jan | B10: 510750
A11: Feb | B11: 484975
A12: Mar | B12: 483530
A13: Apr | B13: 494887.5
A14: May | B14: 673572.5
A15: Jun | B15: 903837.5
A16: Jul | B16: 1041437.5
A17: Aug | B17: 945275
A18: Sep | B18: 681000
A19: Oct | B19: 623375
A20: Nov | B20: 795612.5
A21: Dec | B21: 1045775
A22: Grand Total | B22: 8684027.5
A27: Row Labels | B27: Sum of Units Sold | D27: State | E27: Unit Sold
A28: Alabama | B28: 408500 | D28: =A28 -> Alabama | E28: =B28 -> 408500
A29: Alaska | B29: 312250 | D29: =A29 -> Alaska | E29: =B29 -> 312250
A30: Arizona | B30: 331500 | D30: =A30 -> Arizona | E30: =B30 -> 331500
A31: Arkansas | B31: 255350 | D31: =A31 -> Arkansas | E31: =B31 -> 255350
A32: California | B32: 1037250 | D32: =A32 -> California | E32: =B32 -> 1037250
A33: Colorado | B33: 324250 | D33: =A33 -> Colorado | E33: =B33 -> 324250
A34: Connecticut | B34: 169600 | D34: =A34 -> Connecticut | E34: =B34 -> 169600
A35: Delaware | B35: 205600 | D35: =A35 -> Delaware | E35: =B35 -> 205600
A36: Florida | B36: 1051700 | D36: =A36 -> Florida | E36: =B36 -> 1051700
A37: Georgia | B37: 579350 | D37: =A37 -> Georgia | E37: =B37 -> 579350
A38: Hawaii | B38: 353500 | D38: =A38 -> Hawaii | E38: =B38 -> 353500
A39: Idaho | B39: 288250 | D39: =A39 -> Idaho | E39: =B39 -> 288250
... A77: Wyoming | B77: 310750 | D77: =A77 -> Wyoming | E77: =B77 -> 310750
A78: Grand Total | B78: 17148250

Sheet Dashboard
D2: Key American Retailers | L2: Sum Of Total Sales | N2: Sum Of Units Sold | P2: Sum Of Operating Profit | R2: Average of Margin
L3: =GETPIVOTDATA("Sum of Total Sales",'Piviot Tables'!$A$3) -> 8684027.5 | N3: =GETPIVOTDATA("Sum of Units Sold",'Piviot Tables'!$A$3) -> 17148250 | P3: =GETPIVOTDATA("Sum of Operating Profit",'Piviot Tables'!$A$3) -> 3173631.9 | R3: =GETPIVOTDATA("Average of Operating Margin",'Piviot Tables'!$A$3) -> 0.36310442
